jmespaths/__init__.py
jmespaths/ast.py
jmespaths/compat.py
jmespaths/exceptions.py
jmespaths/functions.py
jmespaths/lexer.py
jmespaths/parser.py
jmespaths/plum.py
jmespaths/visitor.py
jmespaths-1.0.1.6.data/scripts/jp.py
jmespaths-1.0.1.6.dist-info/LICENSE.txt
jmespaths-1.0.1.6.dist-info/METADATA
jmespaths-1.0.1.6.dist-info/WHEEL
jmespaths-1.0.1.6.dist-info/top_level.txt
jmespaths-1.0.1.6.dist-info/RECORD
